[
    {
        "name": "instrument_ctd",
        "type": "i4",
        "attrs": {
            "serial_number": "0126",
            "make_model": "Sea-Bird GPCTD",
            "comment": "Slocum Glider USF Bass",
            "long_name": "Pumped Conductivity, Temperature, Depth (CTD) Sensor",
            "calibration_date": "2013-09-06",
            "user_calibrated": "2013-09-06",
            "factory_calibrated": "2013-09-06",
            "calibration_report": "http://ooma.marine.usf.edu/usf-bass/calibration/seabird_2013/75484R_CD_Contents",
            "type": "instrument",
            "platform": "platform"
        }
    }
]
